une_ai/__init__.py
une_ai/assignments/__init__.py
une_ai/assignments/connect_four_base_environment.py
une_ai/assignments/connect_four_game.py
une_ai/assignments/snake_environment.py
une_ai/assignments/snake_game.py
une_ai/models/MCTS_graph_node.py
une_ai/models/__init__.py
une_ai/models/agent.py
une_ai/models/environment.py
une_ai/models/game_environment.py
une_ai/models/graph_node.py
une_ai/models/grid_map.py
une_ai/models/transposition_table.py
une_ai/tictactoe/__init__.py
une_ai/tictactoe/tictactoc_player.py
une_ai/tictactoe/tictactoe_game.py
une_ai/tictactoe/tictactoe_game_environment.py
une_ai/vacuum/__init__.py
une_ai/vacuum/vacuum_agent.py
une_ai/vacuum/vacuum_dock_environment.py
une_ai/vacuum/vacuum_environment.py
une_ai/vacuum/vacuum_game.py
une_ai-1.1.5.dist-info/LICENSE
une_ai-1.1.5.dist-info/METADATA
une_ai-1.1.5.dist-info/WHEEL
une_ai-1.1.5.dist-info/top_level.txt
une_ai-1.1.5.dist-info/RECORD
