Metadata-Version: 2.1
Name: une_ai
Version: 1.1.5
Summary: Modules used to facilitate the tutorial sessions for UNE unit COSC350/550
Author-email: Jonathan Vitale <jvitale@une.edu.au>
License: MIT License
Keywords: UNE,AI,teaching
Requires-Python: >=3.7
License-File: LICENSE
